setup.py
blockstack_storage_drivers/__init__.py
blockstack_storage_drivers/blockstack_resolver.py
blockstack_storage_drivers/blockstack_server.py
blockstack_storage_drivers/common.py
blockstack_storage_drivers/dht.py
blockstack_storage_drivers/disk.py
blockstack_storage_drivers/http.py
blockstack_storage_drivers/s3.py
blockstack_storage_drivers/version.py
blockstack_storage_drivers.egg-info/PKG-INFO
blockstack_storage_drivers.egg-info/SOURCES.txt
blockstack_storage_drivers.egg-info/dependency_links.txt
blockstack_storage_drivers.egg-info/not-zip-safe
blockstack_storage_drivers.egg-info/requires.txt
blockstack_storage_drivers.egg-info/top_level.txt