Metadata-Version: 1.1
Name: blockstack-storage-drivers
Version: 0.0.1.4
Summary: Back-end storage drivers for Blockstack
Home-page: https://github.com/blockstack/blockstack-storage-drivers
Author: Blockstack.org
Author-email: support@blockstack.org
License: MIT
Download-URL: https://github.com/blockstack/blockstack-storage-drivers/archive/master.zip
Keywords: blockchain bitcoin btc cryptocurrency name key value store data
Platform: UNKNOWN
Classifier: Intended Audience :: Developers
Classifier: License :: OSI Approved :: GNU General Public License v3 (GPLv3)
Classifier: Operating System :: OS Independent
Classifier: Programming Language :: Python
Classifier: Topic :: Internet
Classifier: Topic :: Security :: Cryptography
Classifier: Topic :: Software Development :: Libraries :: Python Modules
